hbcapture/__init__.py
hbcapture/__main__.py
hbcapture/capture.py
hbcapture/data.py
heartbeat_capture-0.7.1.dist-info/LICENSE
heartbeat_capture-0.7.1.dist-info/METADATA
heartbeat_capture-0.7.1.dist-info/WHEEL
heartbeat_capture-0.7.1.dist-info/top_level.txt
heartbeat_capture-0.7.1.dist-info/RECORD
